{
  "category": "install_on_request",
  "total_items": 5,
  "start_date": "2020-05-25",
  "end_date": "2020-08-23",
  "total_count": 7,
  "items": [
    {
      "number": 3909,
      "formula": "nodenv/nodenv/nodenv-aliases",
      "count": "2",
      "percent": "28.57"
    },
    {
      "number": 3910,
      "formula": "nodenv/nodenv/nodenv-default-packages",
      "count": "2",
      "percent": "28.57"
    },
    {
      "number": 5071,
      "formula": "nodenv/nodenv/nodenv-npm-migrate",
      "count": "1",
      "percent": "14.28"
    },
    {
      "number": 5072,
      "formula": "nodenv/nodenv/nodenv-package-json-engine",
      "count": "1",
      "percent": "14.28"
    },
    {
      "number": 5073,
      "formula": "nodenv/nodenv/nodenv-vars",
      "count": "1",
      "percent": "14.28"
    }
  ]
}
