{
  "category": "install_on_request",
  "total_items": 4,
  "start_date": "2020-05-18",
  "end_date": "2020-08-16",
  "total_count": 8,
  "items": [
    {
      "number": 3259,
      "formula": "nodenv/nodenv/nodenv-aliases",
      "count": "3",
      "percent": "37.5"
    },
    {
      "number": 3894,
      "formula": "nodenv/nodenv/nodenv-default-packages",
      "count": "2",
      "percent": "25.0"
    },
    {
      "number": 3895,
      "formula": "nodenv/nodenv/nodenv-vars",
      "count": "2",
      "percent": "25.0"
    },
    {
      "number": 5027,
      "formula": "nodenv/nodenv/nodenv-npm-migrate",
      "count": "1",
      "percent": "12.5"
    }
  ]
}
