{
  "category": "install_on_request",
  "total_items": 5,
  "start_date": "2020-07-16",
  "end_date": "2020-10-14",
  "total_count": 5,
  "items": [
    {
      "number": 4896,
      "formula": "nodenv/nodenv/nodenv-aliases",
      "count": "1",
      "percent": "20.0"
    },
    {
      "number": 4897,
      "formula": "nodenv/nodenv/nodenv-npm-migrate",
      "count": "1",
      "percent": "20.0"
    },
    {
      "number": 4898,
      "formula": "nodenv/nodenv/nodenv-package-json-engine",
      "count": "1",
      "percent": "20.0"
    },
    {
      "number": 4899,
      "formula": "nodenv/nodenv/nodenv-package-rehash",
      "count": "1",
      "percent": "20.0"
    },
    {
      "number": 4900,
      "formula": "nodenv/nodenv/nodenv-vars",
      "count": "1",
      "percent": "20.0"
    }
  ]
}
